Metadata-Version: 1.0
Name: django-rest-schemas
Version: 1.0.1
Summary: for detail control of coreapi by django_rest_framework
Home-page: https://github.com/waipbmtd/django-rest-swagger-schemas
Author: Devin
Author-email: waipbmtd@gmail.com
License: GPL
Platform: UNKNOWN
